hellbox/jobs/fontmake/__init__.py
hellbox/jobs/fontmake/__version__.py
hellbox/jobs/fontmake/generate_otf.py
hellbox/jobs/fontmake/generate_ttf.py
hellbox_fontmake-0.1.1.dist-info/LICENSE
hellbox_fontmake-0.1.1.dist-info/METADATA
hellbox_fontmake-0.1.1.dist-info/WHEEL
hellbox_fontmake-0.1.1.dist-info/top_level.txt
hellbox_fontmake-0.1.1.dist-info/RECORD
