Metadata-Version: 2.1
Name: hellbox-fontmake
Version: 0.1.1
Summary: fontmake job for hellbox.
Home-page: http://github.com/hellboxpy/hellbox-fontmake
Author: Jack Jennings
Author-email: jack@standard-library.com
License: MIT
Platform: UNKNOWN
Classifier: Development Status :: 3 - Alpha
Classifier: Environment :: Plugins
Classifier: License :: OSI Approved :: MIT License
Classifier: Programming Language :: Python :: 3.6
Classifier: Programming Language :: Python :: 3.7
Classifier: Programming Language :: Python :: 3
Classifier: Programming Language :: Python :: Implementation :: CPython
Classifier: Programming Language :: Python
Classifier: Topic :: Software Development :: Build Tools
Requires-Python: >=3.6.0
Requires-Dist: hellbox
Requires-Dist: fontmake
